MANIFEST.in
README.rst
setup.py
SafeSeqS.egg-info/PKG-INFO
SafeSeqS.egg-info/SOURCES.txt
SafeSeqS.egg-info/dependency_links.txt
SafeSeqS.egg-info/requires.txt
SafeSeqS.egg-info/top_level.txt
SafeSeqS.egg-info/zip-safe
safeseqs/__init__.py
safeseqs/align.py
safeseqs/example.py
safeseqs/opticalDuplicates.py
safeseqs/safeseqs_controller.py
safeseqs/sample_super_muts.py
safeseqs/super_mutants.py
safeseqs/uid_stats.py
safeseqs/unique.py
safeseqs/utilities.py
safeseqs/well_super_muts.py
safeseqs.egg-info/PKG-INFO
safeseqs.egg-info/SOURCES.txt
safeseqs.egg-info/dependency_links.txt
safeseqs.egg-info/requires.txt
safeseqs.egg-info/top_level.txt
safeseqs.egg-info/zip-safe
safeseqs/data/COSMIC.txt
safeseqs/data/dbSNP.txt
safeseqs/data/settings.json
safeseqs/example/Primers.txt
safeseqs/example/exampleBarcodeMap.txt
safeseqs/example/example_I1_001.fastq
safeseqs/example/example_R1_001.fastq
safeseqs/example/safeseqs.json