Metadata-Version: 1.1
Name: safeseqs
Version: 0.91
Summary: Safe-SequencingSystem (SafeSeqs) data processing pipeline
Home-page: https://www.ncbi.nlm.nih.gov/pmc/articles/PMC3111315/
Author: Kenneth Kinzler
Author-email: kinzlke@jhmi.edu
License: UNKNOWN
Platform: UNKNOWN
Classifier: Development Status :: 5 - Production/Stable
Classifier: Intended Audience :: Science/Research
Classifier: Topic :: Scientific/Engineering :: Bio-Informatics
